mocs/__init__.py
mocs/__main__.py
mocs/client.py
mocs/common.py
mocs/rule.py
mocs/server/__init__.py
mocs/server/app.py
mocs/server/resource.py
mocs-0.1.3.dist-info/LICENSE.txt
mocs-0.1.3.dist-info/METADATA
mocs-0.1.3.dist-info/RECORD
mocs-0.1.3.dist-info/WHEEL
mocs-0.1.3.dist-info/top_level.txt
