Metadata-Version: 2.1
Name: mocs
Version: 0.1.3
Summary: Http API mock server based on tornado, configurable by REST API.
Home-page: https://github.com/yyang179/mocs
Author: yyang179
Author-email: yyang179@hotmail.com
License: Apache License 2.0
Platform: Posix; MacOS X; Windows
Classifier: Development Status :: 4 - Beta
Classifier: Intended Audience :: Developers
Classifier: License :: OSI Approved :: MIT License
Classifier: Operating System :: OS Independent
Classifier: Topic :: Software Development :: Libraries
Classifier: Topic :: Software Development :: Libraries :: Python Modules
Classifier: Topic :: Software Development :: Testing
Classifier: Programming Language :: Python
Classifier: Programming Language :: Python :: 3.5
Classifier: Programming Language :: Python :: 3.6
Requires-Python: >=3.5
Requires-Dist: tornado
Requires-Dist: jsonschema
Requires-Dist: requests
Requires-Dist: PyYAML
Requires-Dist: coupling (>=0.8.7)
